mdformat_tables/__init__.py
mdformat_tables/plugin.py
mdformat_tables-0.4.1.dist-info/entry_points.txt
mdformat_tables-0.4.1.dist-info/LICENSE
mdformat_tables-0.4.1.dist-info/WHEEL
mdformat_tables-0.4.1.dist-info/METADATA
mdformat_tables-0.4.1.dist-info/RECORD
