Metadata-Version: 1.1
Name: mdformat_tables
Version: 0.4.1
Summary: An mdformat plugin for rendering tables.
Home-page: https://github.com/executablebooks/mdformat-tables
Author: Chris Sewell
Author-email: executablebooks@gmail.com
